alpaka/__init__.py
alpaka/alpaka.py
alpaka/arkitekt.py
alpaka/errors.py
alpaka/funcs.py
alpaka/py.typed
alpaka/rath.py
alpaka/rekuest.py
alpaka/api/project.json
alpaka/api/schema.graphql
alpaka/api/schema.py
alpaka-0.4.0.dist-info/METADATA
alpaka-0.4.0.dist-info/WHEEL
alpaka-0.4.0.dist-info/RECORD
