Metadata-Version: 2.4
Name: alpaka
Version: 0.4.0
Author-email: jhnnsrs <jhnnsrs@gmail.com>
Requires-Python: >=3.11
Requires-Dist: aiohttp<4,>=3.9.5
Requires-Dist: koil>=1.0.0
Requires-Dist: rath>=3.5
Requires-Dist: websockets>=15.0.1
